ast_decompiler/__init__.py
ast_decompiler/check.py
ast_decompiler/decompiler.py
ast_decompiler/py.typed
ast_decompiler-0.5.0.dist-info/LICENSE
ast_decompiler-0.5.0.dist-info/WHEEL
ast_decompiler-0.5.0.dist-info/METADATA
ast_decompiler-0.5.0.dist-info/RECORD
